one_claude/__init__.py
one_claude/__main__.py
one_claude/cli.py
one_claude/config.py
one_claude/backup/__init__.py
one_claude/backup/s3.py
one_claude/core/__init__.py
one_claude/core/file_history.py
one_claude/core/models.py
one_claude/core/parser.py
one_claude/core/scanner.py
one_claude/gist/__init__.py
one_claude/gist/api.py
one_claude/gist/exporter.py
one_claude/gist/importer.py
one_claude/gist/store.py
one_claude/index/__init__.py
one_claude/index/embeddings.py
one_claude/index/indexer.py
one_claude/index/search.py
one_claude/index/vector_store.py
one_claude/llm/__init__.py
one_claude/llm/client.py
one_claude/llm/summarizer.py
one_claude/sync/__init__.py
one_claude/sync/crypto.py
one_claude/sync/discovery.py
one_claude/sync/peer.py
one_claude/sync/protocol.py
one_claude/teleport/__init__.py
one_claude/teleport/executors.py
one_claude/teleport/restore.py
one_claude/teleport/sandbox.py
one_claude/tui/__init__.py
one_claude/tui/app.py
one_claude/tui/screens/__init__.py
one_claude/tui/screens/exports.py
one_claude/tui/screens/gist_modals.py
one_claude/tui/screens/home.py
one_claude/tui/screens/session.py
one_claude/tui/widgets/__init__.py
one_claude-0.1.5.dist-info/METADATA
one_claude-0.1.5.dist-info/WHEEL
one_claude-0.1.5.dist-info/entry_points.txt
one_claude-0.1.5.dist-info/RECORD
